{
  "Animals" : {
          "UrlPreview0" : "https://images.unsplash.com/photo-1535083783855-76ae62b2914e?ixlib=rb-1.2.1&ixid=eyJhcHBfaWQiOjEyMDd9&auto=format&fit=crop&w=675&q=80",
          "Url0" : "https://unsplash.com/photos/7_TTPznVIQI/download?force=true",
	  "Artist0": "David Clode",
	  "Title0" : "Isiolo, Kenya",
	  
          "UrlPreview1" : "https://images.unsplash.com/photo-1574870111867-089730e5a72b?ixlib=rb-1.2.1&auto=format&fit=crop&w=634&q=80",
          "Url1" : "https://unsplash.com/photos/D6TqIa-tWRY/download?force=true",
          "Artist1": "Andy Holmes",
	  "Title1" : "Calgary, AB, Canada",
	  
          "UrlPreview2" : "https://images.unsplash.com/photo-1519664824562-b4bc73f9795a?ixlib=rb-1.2.1&auto=format&fit=crop&w=564&q=80",
          "Url2" : "https://unsplash.com/photos/Iw12lY3koDk/download?force=true",
          "Artist2": "Andreas Dress",
	  "Title2" : "Glen Rose, USA",
	  
          "UrlPreview3" : "https://images.unsplash.com/photo-1591824438708-ce405f36ba3d?ixlib=rb-1.2.1&ixid=eyJhcHBfaWQiOjEyMDd9&auto=format&fit=crop&w=634&q=80",
          "Url3" : "https://unsplash.com/photos/Fbdr6gXJBVY/download?force=true",
	  "Artist3": "Hans-Jurgen Mager",
	  "Title3" : "Kanha Park, India",
	  
          "UrlPreview4" : "https://images.unsplash.com/photo-1534759846116-5799c33ce22a?ixlib=rb-1.2.1&ixid=eyJhcHBfaWQiOjEyMDd9&auto=format&fit=crop&w=688&q=80",
          "Url4" : "https://unsplash.com/photos/wYy3rvvgjAU/download?force=true",
	  "Artist4": "Geran de Klerk",
	  "Title4" : "Kruger National Park",
	  
          "UrlPreview5" : "https://images.unsplash.com/photo-1503656142023-618e7d1f435a?ixlib=rb-1.2.1&auto=format&fit=crop&w=703&q=80",
          "Url5" : "https://unsplash.com/photos/N9s3FjzsstM/download?force=true",
	  "Artist5": "Geran de Klerk",
	  "Title5" : "Chobe National Park",
	  
          "UrlPreview6" : "https://images.unsplash.com/photo-1495012379376-194a416fcc5f?ixlib=rb-1.2.1&auto=format&fit=crop&w=667&q=80",
          "Url6" : "https://unsplash.com/photos/_AjqGGafofE/download?force=true",
	  "Artist6": "Joel Filipe",
	  "Title6" : "Valencia, Spain",
	  
          "UrlPreview7" : "https://images.unsplash.com/photo-1504006833117-8886a355efbf?ixlib=rb-1.2.1&ixid=eyJhcHBfaWQiOjExMjU4fQ&auto=format&fit=crop&w=750&q=80",
          "Url7" : "https://unsplash.com/photos/bKhETeDV1WM/download?force=true",
	  "Artist7": "Geran de Klerk",
	  "Title7" : "Gällivare, Sweden",
	  
          "UrlPreview8" : "https://images.unsplash.com/photo-1462953491269-9aff00919695?ixlib=rb-1.2.1&auto=format&fit=crop&w=634&q=80",
          "Url8" : "https://unsplash.com/photos/HQqIOc8oYro/download?force=true",
	  "Artist8": "Linnea Sandbakk",
	  "Title8" : "Hovedøya, Norway",
	  
          "UrlPreview9" : "https://images.unsplash.com/photo-1430026996702-608b84ce9281?ixlib=rb-1.2.1&ixid=eyJhcHBfaWQiOjEyMDd9&auto=format&fit=crop&w=750&q=80",
          "Url9" : "https://unsplash.com/photos/LOlMe8HfofI/download?force=true",
	  "Artist9": "Lucas Alexander",
	  "Title9" : "Rhinoceros",
	  
	  "UrlPreview10" : "https://images.unsplash.com/photo-1567608580061-0437abed1133?ixlib=rb-1.2.1&auto=format&fit=crop&w=564&q=80",
          "Url10" : "https://unsplash.com/photos/M3xDlTUuix4/download?force=true",
	  "Artist10": "Maurits Bausenhart",
	  "Title10" : "Brown Lion",
	  
	  "UrlPreview11" : "https://images.unsplash.com/photo-1535268647677-300dbf3d78d1?ixlib=rb-1.2.1&ixid=eyJhcHBfaWQiOjEyMDd9&auto=format&fit=crop&w=634&q=80",
          "Url11" : "https://unsplash.com/photos/Wzj7rBxxMaw/download?force=true",
	  "Artist11": "Daniel Octavian",
	  "Title11" : "I See You"
    }
}
